snowpark_connect_deps_1/__init__.py
snowpark_connect_deps_1/jars/spark-catalyst_2.12-3.5.6.jar
snowpark_connect_deps_1/jars/spark-common-utils_2.12-3.5.6.jar
snowpark_connect_deps_1/jars/spark-connect-client-jvm_2.12-3.5.6.jar
snowpark_connect_deps_1/jars/spark-core_2.12-3.5.6.jar
snowpark_connect_deps_1/jars/spark-graphx_2.12-3.5.6.jar
snowpark_connect_deps_1/jars/spark-hive-thriftserver_2.12-3.5.6.jar
snowpark_connect_deps_1/jars/spark-hive_2.12-3.5.6.jar
snowpark_connect_deps_1/jars/spark-kubernetes_2.12-3.5.6.jar
snowpark_connect_deps_1/jars/spark-kvstore_2.12-3.5.6.jar
snowpark_connect_deps_1/jars/spark-launcher_2.12-3.5.6.jar
snowpark_connect_deps_1/jars/spark-mesos_2.12-3.5.6.jar
snowpark_connect_deps_1/jars/spark-mllib-local_2.12-3.5.6.jar
snowpark_connect_deps_1/jars/spark-mllib_2.12-3.5.6.jar
snowpark_connect_deps_1/jars/spark-network-common_2.12-3.5.6.jar
snowpark_connect_deps_1/jars/spark-network-shuffle_2.12-3.5.6.jar
snowpark_connect_deps_1/jars/spark-repl_2.12-3.5.6.jar
snowpark_connect_deps_1/jars/spark-sketch_2.12-3.5.6.jar
snowpark_connect_deps_1/jars/spark-sql-api_2.12-3.5.6.jar
snowpark_connect_deps_1/jars/spark-sql_2.12-3.5.6.jar
snowpark_connect_deps_1/jars/spark-streaming_2.12-3.5.6.jar
snowpark_connect_deps_1/jars/spark-tags_2.12-3.5.6.jar
snowpark_connect_deps_1/jars/spark-unsafe_2.12-3.5.6.jar
snowpark_connect_deps_1/jars/spark-yarn_2.12-3.5.6.jar
snowpark_connect_deps_1-3.56.2.dist-info/licenses/LICENSE-binary
snowpark_connect_deps_1-3.56.2.dist-info/licenses/LICENSE.txt
snowpark_connect_deps_1-3.56.2.dist-info/licenses/NOTICE-binary
snowpark_connect_deps_1-3.56.2.dist-info/METADATA
snowpark_connect_deps_1-3.56.2.dist-info/WHEEL
snowpark_connect_deps_1-3.56.2.dist-info/top_level.txt
snowpark_connect_deps_1-3.56.2.dist-info/RECORD
