Metadata-Version: 2.4
Name: snowpark-connect-deps-1
Version: 3.56.2
Summary: Spark JAR dependencies for Snowpark Connect (Part 1)
Author: Snowflake, Inc
License: Apache License, Version 2.0
Classifier: Development Status :: 5 - Production/Stable
Classifier: Intended Audience :: Developers
Classifier: License :: OSI Approved :: Apache Software License
Classifier: Operating System :: OS Independent
Classifier: Programming Language :: Java
Classifier: Programming Language :: Python :: 3.10
Classifier: Programming Language :: Python :: 3.11
Classifier: Programming Language :: Python :: 3.12
Classifier: Topic :: Software Development :: Libraries
Requires-Python: >=3.10,<3.13
License-File: LICENSE.txt
License-File: LICENSE-binary
License-File: NOTICE-binary
Dynamic: author
Dynamic: classifier
Dynamic: description
Dynamic: description-content-type
Dynamic: license
Dynamic: license-file
Dynamic: requires-python
Dynamic: summary
